LICENSE
README.md
setup.py
fastapi_range_response/__init__.py
fastapi_range_response/_base.py
fastapi_range_response/asyncssh_response.py
fastapi_range_response/exceptions.py
fastapi_range_response/file_response.py
fastapi_range_response.egg-info/PKG-INFO
fastapi_range_response.egg-info/SOURCES.txt
fastapi_range_response.egg-info/dependency_links.txt
fastapi_range_response.egg-info/requires.txt
fastapi_range_response.egg-info/top_level.txt