Metadata-Version: 2.1
Name: fastapi-range-response
Version: 0.1.1
Summary: HTTP range implementation based on Fastapi
Author: wyh
Author-email: 2448979539@qq.com
Requires-Python: >=3.10
License-File: LICENSE
Requires-Dist: requests
Requires-Dist: starlette
Requires-Dist: asyncssh
Requires-Dist: aiofiles
